credential_shield/__init__.py
credential_shield/exceptions.py
credential_shield_fdelgados-2.1.1.dist-info/LICENSE.txt
credential_shield_fdelgados-2.1.1.dist-info/METADATA
credential_shield_fdelgados-2.1.1.dist-info/WHEEL
credential_shield_fdelgados-2.1.1.dist-info/top_level.txt
credential_shield_fdelgados-2.1.1.dist-info/RECORD
