Metadata-Version: 2.1
Name: credential-shield-fdelgados
Version: 2.1.1
Summary: Access tokens validator. Role checker
Home-page: https://github.com/fdelgados/credential-shield.git
Author: Cisco Delgado
Author-email: fdelgados@gmail.com
License: UNKNOWN
Platform: UNKNOWN
Requires-Python: >=3.9
License-File: LICENSE.txt
Requires-Dist: PyJWT (==1.5.3)
Requires-Dist: parse (==1.19.0)
